vgdb_general.py
vgdb_general-0.1.0.dist-info/METADATA
vgdb_general-0.1.0.dist-info/WHEEL
vgdb_general-0.1.0.dist-info/top_level.txt
vgdb_general-0.1.0.dist-info/RECORD
