Metadata-Version: 2.4
Name: vgdb-general
Version: 0.1.0
Summary: Add your description here
Requires-Python: >=3.10
Requires-Dist: requests>=2.32.4
